{
  "hash": "a4b23cd0",
  "configHash": "0caefea3",
  "lockfileHash": "3aef35d7",
  "browserHash": "efaf5919",
  "optimized": {
    "jwt-decode": {
      "src": "../../../../../node_modules/jwt-decode/build/esm/index.js",
      "file": "jwt-decode.js",
      "fileHash": "989c32cf",
      "needsInterop": false
    },
    "dayjs/esm/index": {
      "src": "../../../../../node_modules/dayjs/esm/index.js",
      "file": "dayjs_esm_index.js",
      "fileHash": "78df3be6",
      "needsInterop": false
    },
    "crypto-js": {
      "src": "../../../../../node_modules/crypto-js/index.js",
      "file": "crypto-js.js",
      "fileHash": "24efa751",
      "needsInterop": true
    },
    "uniapp-axios-adapter": {
      "src": "../../../../../node_modules/uniapp-axios-adapter/lib/index.esm.js",
      "file": "uniapp-axios-adapter.js",
      "fileHash": "303ecd3f",
      "needsInterop": false
    },
    "date-fns": {
      "src": "../../../../../node_modules/date-fns/index.js",
      "file": "date-fns.js",
      "fileHash": "5fe5f909",
      "needsInterop": false
    },
    "date-fns/locale": {
      "src": "../../../../../node_modules/date-fns/locale.js",
      "file": "date-fns_locale.js",
      "fileHash": "6a28d82b",
      "needsInterop": false
    }
  },
  "chunks": {
    "chunk-KOF34POV": {
      "file": "chunk-KOF34POV.js"
    },
    "chunk-4337NVKS": {
      "file": "chunk-4337NVKS.js"
    }
  }
}